fabpolish/__init__.py
fabpolish/contrib.py
fab_polish-1.2.0.dist-info/METADATA
fab_polish-1.2.0.dist-info/WHEEL
fab_polish-1.2.0.dist-info/top_level.txt
fab_polish-1.2.0.dist-info/RECORD
