Metadata-Version: 2.1
Name: fab-polish
Version: 1.2.0
Summary: Polish git versioned source code using Fabric
Home-page: https://github.com/practo/FabPolish
Author: J Kishore Kumar
Author-email: kishore@practo.com
License: MIT
Platform: UNKNOWN
Requires-Dist: fabric3 (<2)
